<annotation>
	<folder>Herpes (Numen)</folder>
	<filename>herpes-simplex-022__ProtectWyJQcm90ZWN0Il0_FocusFillWzI5NCwyMjIsIngiLDFd.jpg</filename>
	<path>D:\Universitas Padjadjaran\Bangkit\Capstone\drive-download-20230601T031056Z-001\Herpes (Numen)\herpes-simplex-022__ProtectWyJQcm90ZWN0Il0_FocusFillWzI5NCwyMjIsIngiLDFd.jpg</path>
	<source>
		<database>Unknown</database>
	</source>
	<size>
		<width>294</width>
		<height>222</height>
		<depth>3</depth>
	</size>
	<segmented>0</segmented>
	<object>
		<name>Herpes</name>
		<pose>Unspecified</pose>
		<truncated>1</truncated>
		<difficult>0</difficult>
		<bndbox>
			<xmin>22</xmin>
			<ymin>91</ymin>
			<xmax>127</xmax>
			<ymax>222</ymax>
		</bndbox>
	</object>
	<object>
		<name>Herpes</name>
		<pose>Unspecified</pose>
		<truncated>0</truncated>
		<difficult>0</difficult>
		<bndbox>
			<xmin>112</xmin>
			<ymin>2</ymin>
			<xmax>215</xmax>
			<ymax>74</ymax>
		</bndbox>
	</object>
</annotation>
